non_blocking_io_wrapper/__init__.py
non_blocking_io_wrapper/non_blocking_reader.py
non_blocking_io_wrapper/version.py
non_blocking_io_wrapper-0.7.0.dist-info/LICENCE.txt
non_blocking_io_wrapper-0.7.0.dist-info/METADATA
non_blocking_io_wrapper-0.7.0.dist-info/WHEEL
non_blocking_io_wrapper-0.7.0.dist-info/top_level.txt
non_blocking_io_wrapper-0.7.0.dist-info/RECORD
