Metadata-Version: 2.1
Name: non-blocking-io-wrapper
Version: 0.7.0
Summary: Non blocking io wrapper over an input stream
Home-page: https://github.com/s-ball/non_blocking_io_wrapper
Author: SBA
Author-email: s-ball@laposte.net
License: MIT
Platform: UNKNOWN
Classifier: Development Status :: 4 - Beta
Classifier: Intended Audience :: Developers
Classifier: Operating System :: OS Independent
Classifier: License :: OSI Approved :: MIT License
Classifier: Programming Language :: Python :: 3
Classifier: Programming Language :: Python :: 3.6
Classifier: Programming Language :: Python :: 3.7
Classifier: Programming Language :: Python :: 3.8
Classifier: Topic :: Communications
Requires-Python: >=3.6
